odoo/addons/l10n_it_location_nuts/README.rst
odoo/addons/l10n_it_location_nuts/__init__.py
odoo/addons/l10n_it_location_nuts/__manifest__.py
odoo/addons/l10n_it_location_nuts/hooks.py
odoo/addons/l10n_it_location_nuts/i18n/it.po
odoo/addons/l10n_it_location_nuts/i18n/l10n_it_location_nuts.pot
odoo/addons/l10n_it_location_nuts/readme/CONFIGURE.rst
odoo/addons/l10n_it_location_nuts/readme/CONTRIBUTORS.rst
odoo/addons/l10n_it_location_nuts/readme/DESCRIPTION.rst
odoo/addons/l10n_it_location_nuts/static/description/icon.png
odoo/addons/l10n_it_location_nuts/static/description/index.html
odoo/addons/l10n_it_location_nuts/tests/__init__.py
odoo/addons/l10n_it_location_nuts/tests/test_nuts.py
odoo/addons/l10n_it_location_nuts/wizard/__init__.py
odoo/addons/l10n_it_location_nuts/wizard/nuts_import.py
odoo14_addon_l10n_it_location_nuts-14.0.1.1.0.dist-info/METADATA
odoo14_addon_l10n_it_location_nuts-14.0.1.1.0.dist-info/WHEEL
odoo14_addon_l10n_it_location_nuts-14.0.1.1.0.dist-info/top_level.txt
odoo14_addon_l10n_it_location_nuts-14.0.1.1.0.dist-info/RECORD
